pyDNA_melting/__init__.py
pyDNA_melting/utils.py
pyDNA_melting/scripts/Figure1.jpg
pyDNA_melting/scripts/Figure_1.jpg
pyDNA_melting/scripts/G_NN.m
pyDNA_melting/scripts/LICENSE
pyDNA_melting/scripts/README.md
pyDNA_melting/scripts/count_W10_sum_T1_w00_rand.arff
pyDNA_melting/scripts/count_W10_sum_T1_w06_rand.arff
pyDNA_melting/scripts/count_W10_sum_T2_w00_rand.arff
pyDNA_melting/scripts/count_W10_sum_T2_w06_rand.arff
pyDNA_melting/scripts/count_W10_sum_T3_w00_rand.arff
pyDNA_melting/scripts/count_W10_sum_T3_w06_rand.arff
pyDNA_melting/scripts/count_W15_sum_T1_w00_rand.arff
pyDNA_melting/scripts/count_W15_sum_T1_w06_rand.arff
pyDNA_melting/scripts/count_W15_sum_T2_w00_rand.arff
pyDNA_melting/scripts/count_W15_sum_T2_w06_rand.arff
pyDNA_melting/scripts/count_W20_sum_T1_w00_rand.arff
pyDNA_melting/scripts/count_W20_sum_T1_w06_rand.arff
pyDNA_melting/scripts/count_W5_sum_T1_w00_rand.arff
pyDNA_melting/scripts/count_W5_sum_T1_w06_rand.arff
pyDNA_melting/scripts/count_W5_sum_T2_w00_rand.arff
pyDNA_melting/scripts/count_W5_sum_T2_w06_rand.arff
pyDNA_melting/scripts/count_W5_sum_T3_w00_rand.arff
pyDNA_melting/scripts/count_W5_sum_T3_w06_rand.arff
pyDNA_melting/scripts/count_W5_sum_T4_w00_rand.arff
pyDNA_melting/scripts/count_W5_sum_T4_w06_rand.arff
pyDNA_melting/scripts/dlmcell.m
pyDNA_melting/scripts/dlmcell_rand.m
pyDNA_melting/scripts/job1_W5_T1_w01_rand.arff
pyDNA_melting/scripts/job1_W5_T1_w06_rand.arff
pyDNA_melting/scripts/job1_W5_T2_w03_rand.arff
pyDNA_melting/scripts/job1_W5_T2_w06_rand.arff
pyDNA_melting/scripts/matlab.mat
pyDNA_melting/scripts/nn_therm_data.mat
pyDNA_melting/scripts/nn_therm_loops.mat
pyDNA_melting/scripts/nn_therm_text.mat
pyDNA_melting/scripts/seqcomplement.m
pyDNA_melting/scripts/seqcomplement.m~
pyDNA_melting/scripts/seqreverse.m
pyDNA_melting/scripts/seqreverse.m~
pyDNA_melting/scripts/serv_name.m
pyDNA_melting/scripts/serv_name2.m
pyDNA_melting/scripts/weka.jar
pyDNA_melting/scripts/weka_run.m
pyDNA_melting-2.0.data/scripts/DNA_melting
pyDNA_melting-2.0.dist-info/LICENSE
pyDNA_melting-2.0.dist-info/METADATA
pyDNA_melting-2.0.dist-info/WHEEL
pyDNA_melting-2.0.dist-info/top_level.txt
pyDNA_melting-2.0.dist-info/RECORD
