Metadata-Version: 2.1
Name: pyDNA-melting
Version: 2.0
Summary: Calculate DNA melting score
Home-page: https://github.com/YichaoOU/pyDNA_melting
Author: Yichao Li
Author-email: yl079811@ohio.edu
License: LICENSE
Platform: UNKNOWN
